.DS_Store
tdmca/__init__.py
tdmca/tdmca.py
tdmca-0.1.0.3.dist-info/LICENSE.txt
tdmca-0.1.0.3.dist-info/METADATA
tdmca-0.1.0.3.dist-info/WHEEL
tdmca-0.1.0.3.dist-info/top_level.txt
tdmca-0.1.0.3.dist-info/RECORD
