Metadata-Version: 2.1
Name: tdmca
Version: 0.1.0.3
Summary: A package to calculate Attribution using Markov Chain.
Author: Yannis Marigo
Requires-Python: >=3.6
License-File: LICENSE.txt
Requires-Dist: pandas >=2.1.0
Requires-Dist: numpy
